{
  "active": true,
  "connections": {
    "Webhook": {
      "main": [
        [
          {
            "node": "Trata webhook",
            "type": "main",
            "index": 0
          }
        ]
      ]
    },
    "Trata webhook": {
      "main": [
        [
          {
            "node": "aprovado",
            "type": "main",
            "index": 0
          },
          {
            "node": "Merge",
            "type": "main",
            "index": 1
          }
        ]
      ]
    },
    "aprovada": {
      "main": [
        [
          {
            "node": "novo1",
            "type": "main",
            "index": 0
          }
        ],
        [
          {
            "node": "adiciona comprador1",
            "type": "main",
            "index": 0
          }
        ]
      ]
    },
    "ID Usuário": {
      "main": [
        [
          {
            "node": "Adiciona Tag",
            "type": "main",
            "index": 0
          }
        ]
      ]
    },
    "Adiciona na Lista": {
      "main": [
        []
      ]
    },
    "Adiciona Tag": {
      "main": [
        [
          {
            "node": "Adiciona na Lista",
            "type": "main",
            "index": 0
          }
        ]
      ]
    },
    "novo": {
      "main": [
        [
          {
            "node": "att contact",
            "type": "main",
            "index": 0
          }
        ]
      ]
    },
    "Cria contato": {
      "main": [
        [
          {
            "node": "If",
            "type": "main",
            "index": 0
          }
        ]
      ]
    },
    "att contact": {
      "main": [
        [
          {
            "node": "add tag2",
            "type": "main",
            "index": 0
          }
        ]
      ]
    },
    "existe": {
      "main": [
        [
          {
            "node": "busca contato",
            "type": "main",
            "index": 0
          }
        ]
      ]
    },
    "busca contato": {
      "main": [
        [
          {
            "node": "If1",
            "type": "main",
            "index": 0
          }
        ]
      ]
    },
    "If": {
      "main": [
        [
          {
            "node": "existe",
            "type": "main",
            "index": 0
          }
        ],
        [
          {
            "node": "novo",
            "type": "main",
            "index": 0
          }
        ]
      ]
    },
    "Formata Telefone1": {
      "main": [
        [
          {
            "node": "Cria contato",
            "type": "main",
            "index": 0
          }
        ]
      ]
    },
    "sem nono digito": {
      "main": [
        [
          {
            "node": "busca contato1",
            "type": "main",
            "index": 0
          }
        ]
      ]
    },
    "busca contato1": {
      "main": [
        [
          {
            "node": "add tag1",
            "type": "main",
            "index": 0
          }
        ]
      ]
    },
    "If1": {
      "main": [
        [
          {
            "node": "sem nono digito",
            "type": "main",
            "index": 0
          }
        ],
        [
          {
            "node": "add tag",
            "type": "main",
            "index": 0
          }
        ]
      ]
    },
    "add tag": {
      "main": [
        [
          {
            "node": "envia fluxo",
            "type": "main",
            "index": 0
          }
        ]
      ]
    },
    "add tag1": {
      "main": [
        [
          {
            "node": "envia fluxo1",
            "type": "main",
            "index": 0
          }
        ]
      ]
    },
    "add tag2": {
      "main": [
        [
          {
            "node": "envia fluxo3",
            "type": "main",
            "index": 0
          }
        ]
      ]
    },
    "ActiveCampaign": {
      "main": [
        [
          {
            "node": "Filter",
            "type": "main",
            "index": 0
          }
        ]
      ]
    },
    "ActiveCampaign1": {
      "main": [
        [
          {
            "node": "Filter1",
            "type": "main",
            "index": 0
          }
        ]
      ]
    },
    "adiciona comprador": {
      "main": [
        [
          {
            "node": "ID Usuário",
            "type": "main",
            "index": 0
          }
        ]
      ]
    },
    "aprovado": {
      "main": [
        [
          {
            "node": "busca evento",
            "type": "main",
            "index": 0
          }
        ],
        []
      ]
    },
    "busca evento": {
      "main": [
        [
          {
            "node": "existe1",
            "type": "main",
            "index": 0
          }
        ]
      ]
    },
    "existe1": {
      "main": [
        [],
        [
          {
            "node": "Merge",
            "type": "main",
            "index": 0
          },
          {
            "node": "add evento",
            "type": "main",
            "index": 0
          }
        ]
      ]
    },
    "Merge": {
      "main": [
        [
          {
            "node": "aprovada",
            "type": "main",
            "index": 0
          }
        ]
      ]
    },
    "novo1": {
      "main": [
        [
          {
            "node": "Formata Telefone1",
            "type": "main",
            "index": 0
          },
          {
            "node": "adiciona comprador",
            "type": "main",
            "index": 0
          },
          {
            "node": "Notifica grupo | Renan2",
            "type": "main",
            "index": 0
          }
        ]
      ]
    }
  },
  "createdAt": "2025-09-10T18:03:23.683Z",
  "id": "IWuNDg2leQAk25ev",
  "isArchived": false,
  "meta": {
    "templateCredsSetupCompleted": true
  },
  "name": "[CAROL][IP EXPRESS][PAGO][SETEMBRO] Compradores",
  "nodes": [
    {
      "parameters": {
        "httpMethod": "POST",
        "path": "compradores-ip-express",
        "options": {}
      },
      "type": "n8n-nodes-base.webhook",
      "typeVersion": 2,
      "position": [
        -900,
        0
      ],
      "id": "b5f86ceb-f3b8-4fec-956e-ae2c51f33ea8",
      "name": "Webhook",
      "webhookId": "99e0f8b6-94d3-4a55-bc75-1ba963906a39"
    },
    {
      "parameters": {
        "jsCode": "return typeof $node[\"Webhook\"].json[\"body\"] == 'string' ? JSON.parse($node[\"Webhook\"].json[\"body\"]) : $node[\"Webhook\"].json[\"body\"]\n"
      },
      "id": "70ef541a-d2f6-4e8f-ad2a-86030825b48a",
      "name": "Trata webhook",
      "type": "n8n-nodes-base.code",
      "typeVersion": 1,
      "position": [
        -680,
        0
      ]
    },
    {
      "parameters": {
        "conditions": {
          "options": {
            "caseSensitive": true,
            "leftValue": "",
            "typeValidation": "strict",
            "version": 2
          },
          "conditions": [
            {
              "id": "34ebb34a-a8d8-4405-a445-78e2b6207df3",
              "leftValue": "={{ $json.status }}",
              "rightValue": "approved",
              "operator": {
                "type": "string",
                "operation": "equals",
                "name": "filter.operator.equals"
              }
            }
          ],
          "combinator": "and"
        },
        "options": {}
      },
      "type": "n8n-nodes-base.if",
      "typeVersion": 2.2,
      "position": [
        380,
        -20
      ],
      "id": "396d2abb-c33f-4e45-8bce-464bce63b38b",
      "name": "aprovada"
    },
    {
      "parameters": {
        "operation": "append",
        "documentId": {
          "__rl": true,
          "value": "https://docs.google.com/spreadsheets/d/1PJ7sUI90q7YemvstNJWLRu8SMFZzfMQo7PQPU6FJ4gw/edit?usp=sharing",
          "mode": "url"
        },
        "sheetName": {
          "__rl": true,
          "value": "gid=0",
          "mode": "list",
          "cachedResultName": "compradores",
          "cachedResultUrl": "https://docs.google.com/spreadsheets/d/1PJ7sUI90q7YemvstNJWLRu8SMFZzfMQo7PQPU6FJ4gw/edit#gid=0"
        },
        "columns": {
          "mappingMode": "defineBelow",
          "value": {
            "data": "={{ $now.format(\"dd/MM/yyyy\") }}",
            "nome": "={{ $json.contact.name }}",
            "email": "={{ $json.contact.email }}",
            "telefone": "={{ $json.contact.phone_number }}",
            "oferta": "={{ $json.items[0].total_value }}",
            "utm_source": "={{ $json.source.utm_source }}",
            "utm_campaign": "={{ $json.source.utm_campaign }}",
            "utm_medium": "={{ $json.source.utm_medium }}",
            "utm_content": "={{ $json.source.utm_content }}",
            "utm_term": "={{ $json.source.utm_term }}"
          },
          "matchingColumns": [],
          "schema": [
            {
              "id": "data",
              "displayName": "data",
              "required": false,
              "defaultMatch": false,
              "display": true,
              "type": "string",
              "canBeUsedToMatch": true
            },
            {
              "id": "nome",
              "displayName": "nome",
              "required": false,
              "defaultMatch": false,
              "display": true,
              "type": "string",
              "canBeUsedToMatch": true
            },
            {
              "id": "email",
              "displayName": "email",
              "required": false,
              "defaultMatch": false,
              "display": true,
              "type": "string",
              "canBeUsedToMatch": true
            },
            {
              "id": "telefone",
              "displayName": "telefone",
              "required": false,
              "defaultMatch": false,
              "display": true,
              "type": "string",
              "canBeUsedToMatch": true
            },
            {
              "id": "oferta",
              "displayName": "oferta",
              "required": false,
              "defaultMatch": false,
              "display": true,
              "type": "string",
              "canBeUsedToMatch": true
            },
            {
              "id": "utm_source",
              "displayName": "utm_source",
              "required": false,
              "defaultMatch": false,
              "display": true,
              "type": "string",
              "canBeUsedToMatch": true
            },
            {
              "id": "utm_campaign",
              "displayName": "utm_campaign",
              "required": false,
              "defaultMatch": false,
              "display": true,
              "type": "string",
              "canBeUsedToMatch": true
            },
            {
              "id": "utm_medium",
              "displayName": "utm_medium",
              "required": false,
              "defaultMatch": false,
              "display": true,
              "type": "string",
              "canBeUsedToMatch": true
            },
            {
              "id": "utm_content",
              "displayName": "utm_content",
              "required": false,
              "defaultMatch": false,
              "display": true,
              "type": "string",
              "canBeUsedToMatch": true
            },
            {
              "id": "utm_term",
              "displayName": "utm_term",
              "required": false,
              "defaultMatch": false,
              "display": true,
              "type": "string",
              "canBeUsedToMatch": true
            }
          ],
          "attemptToConvertTypes": false,
          "convertFieldsToString": false
        },
        "options": {}
      },
      "type": "n8n-nodes-base.googleSheets",
      "typeVersion": 4.5,
      "position": [
        660,
        -1720
      ],
      "id": "35d2ed09-5d0f-458c-9b63-3954e92d1c95",
      "name": "adiciona comprador",
      "credentials": {
        "googleSheetsOAuth2Api": {
          "id": "PLr9msB1lyoRblyJ",
          "name": "Matheus BMA"
        }
      }
    },
    {
      "parameters": {
        "email": "={{ $item(\"0\").$node[\"Trata webhook\"].json[\"contact\"][\"email\"] }}",
        "updateIfExists": true,
        "additionalFields": {
          "firstName": "={{ $item(\"0\").$node[\"Trata webhook\"].json[\"contact\"][\"name\"] }}",
          "phone": "={{ $item(\"0\").$node[\"Trata webhook\"].json[\"contact\"][\"phone_number\"] }}"
        }
      },
      "id": "958deb6c-9039-4855-972f-0afaffdd1f4a",
      "name": "ID Usuário",
      "type": "n8n-nodes-base.activeCampaign",
      "typeVersion": 1,
      "position": [
        900,
        -1720
      ],
      "retryOnFail": true,
      "maxTries": 5,
      "waitBetweenTries": 5000,
      "credentials": {
        "activeCampaignApi": {
          "id": "4ygJeCXAzG5KRUPW",
          "name": "Active Carol"
        }
      }
    },
    {
      "parameters": {
        "resource": "contactList",
        "listId": 237,
        "contactId": "={{ $('ID Usuário').item.json.id }}"
      },
      "id": "e5b5106b-6b19-4e39-b54b-dbe77d518f9f",
      "name": "Adiciona na Lista",
      "type": "n8n-nodes-base.activeCampaign",
      "typeVersion": 1,
      "position": [
        1280,
        -1720
      ],
      "retryOnFail": true,
      "maxTries": 5,
      "waitBetweenTries": 5000,
      "credentials": {
        "activeCampaignApi": {
          "id": "4ygJeCXAzG5KRUPW",
          "name": "Active Carol"
        }
      }
    },
    {
      "parameters": {
        "resource": "contactTag",
        "tagId": "=1518",
        "contactId": "={{ $json.id }}"
      },
      "id": "fd7e6a6b-2715-4349-abd8-772ea906c2f8",
      "name": "Adiciona Tag",
      "type": "n8n-nodes-base.activeCampaign",
      "typeVersion": 1,
      "position": [
        1100,
        -1720
      ],
      "retryOnFail": true,
      "maxTries": 5,
      "waitBetweenTries": 5000,
      "credentials": {
        "activeCampaignApi": {
          "id": "4ygJeCXAzG5KRUPW",
          "name": "Active Carol"
        }
      }
    },
    {
      "parameters": {},
      "type": "n8n-nodes-base.noOp",
      "typeVersion": 1,
      "position": [
        1400,
        -860
      ],
      "id": "1d8ec9ef-e8d8-41bf-bd10-2e17b639b17c",
      "name": "novo"
    },
    {
      "parameters": {
        "method": "POST",
        "url": "https://api.manychat.com/fb/subscriber/createSubscriber",
        "sendHeaders": true,
        "headerParameters": {
          "parameters": [
            {
              "name": "Authorization",
              "value": "Bearer 2668563:65dc8b763e88cf8b9b0955b1871493fc"
            },
            {
              "name": "Content-Type",
              "value": "application/json"
            }
          ]
        },
        "sendBody": true,
        "specifyBody": "json",
        "jsonBody": "={\n  \"phone\": \"{{\"+\"+ $json.numerosFormatados.comNonoDigito }}\",\n  \"whatsapp_phone\": \"{{\"+\"+ $json.numerosFormatados.comNonoDigito }}\",\n  \"has_opt_in_sms\": false,\n  \"has_opt_in_email\": false,\n  \"consent_phrase\": \"string\"\n} ",
        "options": {}
      },
      "id": "94f13fec-071b-4bdd-831e-2fae995353fc",
      "name": "Cria contato",
      "type": "n8n-nodes-base.httpRequest",
      "typeVersion": 4.2,
      "position": [
        860,
        -940
      ],
      "retryOnFail": false,
      "onError": "continueRegularOutput"
    },
    {
      "parameters": {
        "method": "POST",
        "url": "https://api.manychat.com/fb/subscriber/setCustomField",
        "sendHeaders": true,
        "headerParameters": {
          "parameters": [
            {
              "name": "Authorization",
              "value": "Bearer 2668563:65dc8b763e88cf8b9b0955b1871493fc"
            },
            {
              "name": "Content-Type",
              "value": "application/json"
            }
          ]
        },
        "sendBody": true,
        "bodyParameters": {
          "parameters": [
            {
              "name": "subscriber_id",
              "value": "={{ $node[\"Cria contato\"].json[\"data\"][\"id\"] }}"
            },
            {
              "name": "field_id",
              "value": "12789794"
            },
            {
              "name": "field_value",
              "value": "={{ $node[\"Formata Telefone1\"].json[\"numerosFormatados\"][\"comNonoDigito\"] }}"
            }
          ]
        },
        "options": {}
      },
      "id": "e75b9141-9f41-4ed6-84dc-4ff86089a9ee",
      "name": "att contact",
      "type": "n8n-nodes-base.httpRequest",
      "typeVersion": 4.2,
      "position": [
        1620,
        -860
      ],
      "retryOnFail": false,
      "onError": "continueErrorOutput"
    },
    {
      "parameters": {},
      "type": "n8n-nodes-base.noOp",
      "typeVersion": 1,
      "position": [
        1400,
        -1240
      ],
      "id": "c44c02cf-b59e-47d4-9282-781358499833",
      "name": "existe"
    },
    {
      "parameters": {
        "url": "=https://api.manychat.com/fb/subscriber/findByCustomField?field_id=12789794&field_value={{ $('Formata Telefone1').item.json.numerosFormatados.comNonoDigito }}",
        "sendHeaders": true,
        "headerParameters": {
          "parameters": [
            {
              "name": "Authorization",
              "value": "Bearer 2668563:65dc8b763e88cf8b9b0955b1871493fc"
            },
            {
              "name": "Content-Type",
              "value": "application/json"
            }
          ]
        },
        "options": {}
      },
      "id": "f9a11c64-8529-4110-80ae-777734135fc1",
      "name": "busca contato",
      "type": "n8n-nodes-base.httpRequest",
      "typeVersion": 4.2,
      "position": [
        1620,
        -1240
      ],
      "retryOnFail": false,
      "onError": "continueErrorOutput"
    },
    {
      "parameters": {
        "conditions": {
          "options": {
            "caseSensitive": true,
            "leftValue": "",
            "typeValidation": "strict"
          },
          "conditions": [
            {
              "id": "4b47ac03-1259-4e8c-9e8e-22786f6bf427",
              "leftValue": "={{ $json.error.message }}",
              "rightValue": "This WhatsApp ID already exists",
              "operator": {
                "type": "string",
                "operation": "contains"
              }
            }
          ],
          "combinator": "and"
        },
        "options": {}
      },
      "id": "c00318bb-265b-43b9-ac60-a034b3cd6910",
      "name": "If",
      "type": "n8n-nodes-base.if",
      "typeVersion": 2.1,
      "position": [
        1120,
        -940
      ]
    },
    {
      "parameters": {
        "jsCode": "function formataTelefone(number) {\n    number = number.toString().replace(/[^\\d]/g, \"\");\n    let ddi = \"55\";\n    let ddd, telefone;\n\n    if (number.length === 13) {\n        ddi = number.substring(0, 2);\n        ddd = number.substring(2, 4);\n        telefone = number.substring(4);\n    } else if (number.length === 12) {\n        if (number.startsWith(\"55\")) {\n            ddd = number.substring(2, 4);\n            telefone = number.substring(4);\n        } else if (number.startsWith(\"0\")) {\n            return formataTelefone(number.substring(1));\n        } else {\n            return { comNonoDigito: number, semNonoDigito: number };\n        }\n    } else if (number.length === 11) {\n        ddd = number.substring(0, 2);\n        telefone = number.substring(2);\n    } else if (number.length === 10) {\n        ddd = number.substring(0, 2);\n        telefone = \"9\" + number.substring(2);\n    } else {\n        return { comNonoDigito: number, semNonoDigito: number };\n    }\n\n    let telefoneComNono = telefone.length === 8 ? \"9\" + telefone : telefone;\n    let telefoneSemNono = telefoneComNono.startsWith(\"9\") ? telefoneComNono.substring(1) : telefoneComNono;\n\n    return {\n        comNonoDigito: ddi + ddd + telefoneComNono,\n        semNonoDigito: ddi + ddd + telefoneSemNono\n    };\n}\n\nlet numerosFormatados = formataTelefone($input.first().json.contact.phone_number);\n\n$input.all()[0].json[\"numerosFormatados\"] = numerosFormatados\nreturn $input.all();\n"
      },
      "id": "6c0b545a-db85-4701-9195-24bff55889e7",
      "name": "Formata Telefone1",
      "type": "n8n-nodes-base.code",
      "typeVersion": 1,
      "position": [
        640,
        -940
      ]
    },
    {
      "parameters": {},
      "type": "n8n-nodes-base.noOp",
      "typeVersion": 1,
      "position": [
        2140,
        -1440
      ],
      "id": "8a57ae1d-5ca8-4c31-bc07-99a55fa7bbdf",
      "name": "sem nono digito"
    },
    {
      "parameters": {
        "url": "=https://api.manychat.com/fb/subscriber/findByCustomField?field_id=12789794&field_value={{$node[\"Formata Telefone1\"].json[\"numerosFormatados\"][\"semNonoDigito\"] }}",
        "sendHeaders": true,
        "headerParameters": {
          "parameters": [
            {
              "name": "Authorization",
              "value": "Bearer 2668563:65dc8b763e88cf8b9b0955b1871493fc"
            },
            {
              "name": "Content-Type",
              "value": "application/json"
            }
          ]
        },
        "options": {}
      },
      "id": "6b80716e-fc53-4df4-a3ed-5a093ce8fbe3",
      "name": "busca contato1",
      "type": "n8n-nodes-base.httpRequest",
      "typeVersion": 4.2,
      "position": [
        2340,
        -1440
      ],
      "retryOnFail": false,
      "onError": "continueErrorOutput"
    },
    {
      "parameters": {
        "conditions": {
          "options": {
            "caseSensitive": true,
            "leftValue": "",
            "typeValidation": "strict"
          },
          "conditions": [
            {
              "id": "49a86e22-a9c4-4d6a-b179-2a4335dbb72e",
              "leftValue": "={{ $json.data }}",
              "rightValue": "",
              "operator": {
                "type": "array",
                "operation": "empty",
                "singleValue": true
              }
            }
          ],
          "combinator": "and"
        },
        "options": {}
      },
      "id": "59079090-9579-454a-8743-dc54085804dd",
      "name": "If1",
      "type": "n8n-nodes-base.if",
      "typeVersion": 2.1,
      "position": [
        1900,
        -1260
      ]
    },
    {
      "parameters": {
        "method": "POST",
        "url": "https://api.manychat.com/fb/subscriber/addTag",
        "sendHeaders": true,
        "headerParameters": {
          "parameters": [
            {
              "name": "Authorization",
              "value": "Bearer 992532:cc8fa1dc88700e115938c625cc148dc6"
            },
            {
              "name": "Content-Type",
              "value": "application/json"
            }
          ]
        },
        "sendBody": true,
        "bodyParameters": {
          "parameters": [
            {
              "name": "subscriber_id",
              "value": "={{ $json.data[0].id }}"
            },
            {
              "name": "tag_id",
              "value": "61006975"
            }
          ]
        },
        "options": {}
      },
      "id": "e6d758cc-3ab7-44fb-9b99-f4bab6be7af4",
      "name": "add tag",
      "type": "n8n-nodes-base.httpRequest",
      "typeVersion": 4.2,
      "position": [
        2140,
        -1240
      ],
      "retryOnFail": false,
      "disabled": true,
      "onError": "continueErrorOutput"
    },
    {
      "parameters": {
        "method": "POST",
        "url": "https://api.manychat.com/fb/subscriber/addTag",
        "sendHeaders": true,
        "headerParameters": {
          "parameters": [
            {
              "name": "Authorization",
              "value": "Bearer 992532:cc8fa1dc88700e115938c625cc148dc6"
            },
            {
              "name": "Content-Type",
              "value": "application/json"
            }
          ]
        },
        "sendBody": true,
        "bodyParameters": {
          "parameters": [
            {
              "name": "subscriber_id",
              "value": "={{ $json.data[0].id }}"
            },
            {
              "name": "tag_id",
              "value": "61006975"
            }
          ]
        },
        "options": {}
      },
      "id": "82408241-e717-4cd2-8f54-59c0880b7dc1",
      "name": "add tag1",
      "type": "n8n-nodes-base.httpRequest",
      "typeVersion": 4.2,
      "position": [
        2780,
        -1460
      ],
      "retryOnFail": false,
      "disabled": true,
      "onError": "continueErrorOutput"
    },
    {
      "parameters": {
        "method": "POST",
        "url": "https://api.manychat.com/fb/subscriber/addTag",
        "sendHeaders": true,
        "headerParameters": {
          "parameters": [
            {
              "name": "Authorization",
              "value": "Bearer 992532:cc8fa1dc88700e115938c625cc148dc6"
            },
            {
              "name": "Content-Type",
              "value": "application/json"
            }
          ]
        },
        "sendBody": true,
        "bodyParameters": {
          "parameters": [
            {
              "name": "subscriber_id",
              "value": "={{ $json.data[0].id }}"
            },
            {
              "name": "tag_id",
              "value": "61006975"
            }
          ]
        },
        "options": {}
      },
      "id": "4ab43934-5823-410b-b991-464d19c31fdf",
      "name": "add tag2",
      "type": "n8n-nodes-base.httpRequest",
      "typeVersion": 4.2,
      "position": [
        1920,
        -880
      ],
      "retryOnFail": false,
      "disabled": true,
      "onError": "continueErrorOutput"
    },
    {
      "parameters": {
        "method": "POST",
        "url": "https://api.manychat.com/fb/sending/sendFlow",
        "sendHeaders": true,
        "headerParameters": {
          "parameters": [
            {
              "name": "Authorization",
              "value": "Bearer 2668563:65dc8b763e88cf8b9b0955b1871493fc"
            },
            {
              "name": "Content-Type",
              "value": "application/json"
            }
          ]
        },
        "sendBody": true,
        "bodyParameters": {
          "parameters": [
            {
              "name": "subscriber_id",
              "value": "={{ $node[\"busca contato1\"].json[\"data\"][\"0\"][\"id\"] }}"
            },
            {
              "name": "flow_ns",
              "value": "content20250911193709_233641"
            }
          ]
        },
        "options": {}
      },
      "id": "f74c2554-cb56-457f-8338-db090fca4582",
      "name": "envia fluxo1",
      "type": "n8n-nodes-base.httpRequest",
      "typeVersion": 4.2,
      "position": [
        3100,
        -1480
      ],
      "retryOnFail": false,
      "onError": "continueErrorOutput"
    },
    {
      "parameters": {
        "method": "POST",
        "url": "https://api.manychat.com/fb/sending/sendFlow",
        "sendHeaders": true,
        "headerParameters": {
          "parameters": [
            {
              "name": "Authorization",
              "value": "Bearer 2668563:65dc8b763e88cf8b9b0955b1871493fc"
            },
            {
              "name": "Content-Type",
              "value": "application/json"
            }
          ]
        },
        "sendBody": true,
        "bodyParameters": {
          "parameters": [
            {
              "name": "subscriber_id",
              "value": "={{ $node[\"busca contato\"].json[\"data\"][\"0\"][\"id\"] }}"
            },
            {
              "name": "flow_ns",
              "value": "content20250911193709_233641"
            }
          ]
        },
        "options": {}
      },
      "id": "5a514ef7-b56d-4119-97f4-58e2ec1a6da2",
      "name": "envia fluxo",
      "type": "n8n-nodes-base.httpRequest",
      "typeVersion": 4.2,
      "position": [
        2480,
        -1260
      ],
      "retryOnFail": false,
      "onError": "continueErrorOutput"
    },
    {
      "parameters": {
        "method": "POST",
        "url": "https://api.manychat.com/fb/sending/sendFlow",
        "sendHeaders": true,
        "headerParameters": {
          "parameters": [
            {
              "name": "Authorization",
              "value": "Bearer 2668563:65dc8b763e88cf8b9b0955b1871493fc"
            },
            {
              "name": "Content-Type",
              "value": "application/json"
            }
          ]
        },
        "sendBody": true,
        "bodyParameters": {
          "parameters": [
            {
              "name": "subscriber_id",
              "value": "={{ $node[\"Cria contato\"].json[\"data\"][\"id\"] }}"
            },
            {
              "name": "flow_ns",
              "value": "content20250911193709_233641"
            }
          ]
        },
        "options": {}
      },
      "id": "ae00c51b-dfac-47ff-9f5b-142be47f3c3e",
      "name": "envia fluxo3",
      "type": "n8n-nodes-base.httpRequest",
      "typeVersion": 4.2,
      "position": [
        2280,
        -900
      ],
      "retryOnFail": false,
      "onError": "continueErrorOutput"
    },
    {
      "parameters": {
        "resource": "list",
        "returnAll": true
      },
      "type": "n8n-nodes-base.activeCampaign",
      "typeVersion": 1,
      "position": [
        180,
        560
      ],
      "id": "6533c0c8-bf1a-4e99-920b-4743dec12567",
      "name": "ActiveCampaign",
      "credentials": {
        "activeCampaignApi": {
          "id": "4ygJeCXAzG5KRUPW",
          "name": "Active Carol"
        }
      }
    },
    {
      "parameters": {
        "conditions": {
          "options": {
            "caseSensitive": true,
            "leftValue": "",
            "typeValidation": "strict",
            "version": 2
          },
          "conditions": [
            {
              "id": "e77ae664-ed28-42b5-9f2a-9d4ade4fb1b1",
              "leftValue": "={{ $json.name }}",
              "rightValue": "ip-express-setembro2025-compradores",
              "operator": {
                "type": "string",
                "operation": "equals",
                "name": "filter.operator.equals"
              }
            }
          ],
          "combinator": "and"
        },
        "options": {}
      },
      "type": "n8n-nodes-base.filter",
      "typeVersion": 2.2,
      "position": [
        400,
        560
      ],
      "id": "821ba206-92ed-46ad-86ed-deb714f48d9e",
      "name": "Filter"
    },
    {
      "parameters": {
        "resource": "tag",
        "operation": "getAll",
        "returnAll": true
      },
      "type": "n8n-nodes-base.activeCampaign",
      "typeVersion": 1,
      "position": [
        180,
        800
      ],
      "id": "d0b6470a-d5c5-48ad-b3ef-0ec84d3d8a47",
      "name": "ActiveCampaign1",
      "credentials": {
        "activeCampaignApi": {
          "id": "4ygJeCXAzG5KRUPW",
          "name": "Active Carol"
        }
      }
    },
    {
      "parameters": {
        "conditions": {
          "options": {
            "caseSensitive": true,
            "leftValue": "",
            "typeValidation": "strict",
            "version": 2
          },
          "conditions": [
            {
              "id": "e77ae664-ed28-42b5-9f2a-9d4ade4fb1b1",
              "leftValue": "={{ $json.tag }}",
              "rightValue": "ip-express-setembro2025-compradores",
              "operator": {
                "type": "string",
                "operation": "equals",
                "name": "filter.operator.equals"
              }
            }
          ],
          "combinator": "and"
        },
        "options": {}
      },
      "type": "n8n-nodes-base.filter",
      "typeVersion": 2.2,
      "position": [
        400,
        800
      ],
      "id": "5ac467f8-de19-46ca-8237-ed582a3b885a",
      "name": "Filter1"
    },
    {
      "parameters": {
        "operation": "append",
        "documentId": {
          "__rl": true,
          "value": "https://docs.google.com/spreadsheets/d/1PJ7sUI90q7YemvstNJWLRu8SMFZzfMQo7PQPU6FJ4gw/edit?usp=sharing",
          "mode": "url"
        },
        "sheetName": {
          "__rl": true,
          "value": 609726885,
          "mode": "list",
          "cachedResultName": "recuperação",
          "cachedResultUrl": "https://docs.google.com/spreadsheets/d/1PJ7sUI90q7YemvstNJWLRu8SMFZzfMQo7PQPU6FJ4gw/edit#gid=609726885"
        },
        "columns": {
          "mappingMode": "defineBelow",
          "value": {
            "data": "={{ $now.format(\"dd/MM/yyyy\") }}",
            "nome": "={{ $json.contact.name }}",
            "email": "={{ $json.contact.email }}",
            "telefone": "={{ $json.contact.phone_number }}",
            "oferta": "={{ $json.items[0].total_value }}",
            "utm_source": "={{ $json.source.utm_source }}",
            "utm_campaign": "={{ $json.source.utm_campaign }}",
            "utm_medium": "={{ $json.source.utm_medium }}",
            "utm_content": "={{ $json.source.utm_content }}",
            "utm_term": "={{ $json.source.utm_term }}"
          },
          "matchingColumns": [],
          "schema": [
            {
              "id": "data",
              "displayName": "data",
              "required": false,
              "defaultMatch": false,
              "display": true,
              "type": "string",
              "canBeUsedToMatch": true
            },
            {
              "id": "nome",
              "displayName": "nome",
              "required": false,
              "defaultMatch": false,
              "display": true,
              "type": "string",
              "canBeUsedToMatch": true
            },
            {
              "id": "email",
              "displayName": "email",
              "required": false,
              "defaultMatch": false,
              "display": true,
              "type": "string",
              "canBeUsedToMatch": true
            },
            {
              "id": "telefone",
              "displayName": "telefone",
              "required": false,
              "defaultMatch": false,
              "display": true,
              "type": "string",
              "canBeUsedToMatch": true
            },
            {
              "id": "oferta",
              "displayName": "oferta",
              "required": false,
              "defaultMatch": false,
              "display": true,
              "type": "string",
              "canBeUsedToMatch": true
            },
            {
              "id": "utm_source",
              "displayName": "utm_source",
              "required": false,
              "defaultMatch": false,
              "display": true,
              "type": "string",
              "canBeUsedToMatch": true
            },
            {
              "id": "utm_campaign",
              "displayName": "utm_campaign",
              "required": false,
              "defaultMatch": false,
              "display": true,
              "type": "string",
              "canBeUsedToMatch": true
            },
            {
              "id": "utm_medium",
              "displayName": "utm_medium",
              "required": false,
              "defaultMatch": false,
              "display": true,
              "type": "string",
              "canBeUsedToMatch": true
            },
            {
              "id": "utm_content",
              "displayName": "utm_content",
              "required": false,
              "defaultMatch": false,
              "display": true,
              "type": "string",
              "canBeUsedToMatch": true
            },
            {
              "id": "utm_term",
              "displayName": "utm_term",
              "required": false,
              "defaultMatch": false,
              "display": true,
              "type": "string",
              "canBeUsedToMatch": true
            },
            {
              "id": "comprou",
              "displayName": "comprou",
              "required": false,
              "defaultMatch": false,
              "display": true,
              "type": "string",
              "canBeUsedToMatch": true
            }
          ],
          "attemptToConvertTypes": false,
          "convertFieldsToString": false
        },
        "options": {}
      },
      "type": "n8n-nodes-base.googleSheets",
      "typeVersion": 4.5,
      "position": [
        760,
        0
      ],
      "id": "e90b088c-bde7-4ad9-ba30-f34e52da4047",
      "name": "adiciona comprador1",
      "credentials": {
        "googleSheetsOAuth2Api": {
          "id": "PLr9msB1lyoRblyJ",
          "name": "Matheus BMA"
        }
      }
    },
    {
      "parameters": {
        "method": "POST",
        "url": "https://api.z-api.io/instances/3CFE88963A26408D365B72B70F2FFCF9/token/DA84CEA8EC9897345A31EA92/send-text",
        "sendHeaders": true,
        "headerParameters": {
          "parameters": [
            {
              "name": "Client-Token",
              "value": "Fdeb892ca62d941adbb85b2ec7c8e3a4aS"
            }
          ]
        },
        "sendBody": true,
        "bodyParameters": {
          "parameters": [
            {
              "name": "phone",
              "value": "=120363285621576178-group"
            },
            {
              "name": "message",
              "value": "=*+1 venda IP EXPRESS*\n\nnome: {{ $json.contact.name }}\nemail: {{ $json.contact.email }}\ntelefone: {{ $json.contact.phone_number }}\n\nutm_source: {{ $json.source.utm_source }}\nutm_campaign: {{ $json.source.utm_campaign }}\nutm_medium: {{ $json.source.utm_medium }}\nutm_content: {{ $json.source.utm_content }}\nutm_term: {{ $json.source.utm_term }}"
            }
          ]
        },
        "options": {}
      },
      "id": "7c29895f-417a-4427-9774-27ecc682e54e",
      "name": "Notifica grupo | Renan2",
      "type": "n8n-nodes-base.httpRequest",
      "typeVersion": 4.2,
      "position": [
        680,
        -2000
      ],
      "retryOnFail": true,
      "maxTries": 5,
      "waitBetweenTries": 5000
    },
    {
      "parameters": {
        "operation": "getAll",
        "tableId": "eventos_guru",
        "returnAll": true,
        "matchType": "allFilters",
        "filters": {
          "conditions": [
            {
              "keyName": "id_contato",
              "condition": "eq",
              "keyValue": "={{ $json.contact.id }}"
            },
            {
              "keyName": "id_oferta",
              "condition": "eq",
              "keyValue": "={{ $json.items[0].offer.id }}"
            }
          ]
        }
      },
      "type": "n8n-nodes-base.supabase",
      "typeVersion": 1,
      "position": [
        -440,
        -240
      ],
      "id": "fc07436a-90c9-4324-b6cf-a68f0a1c10e6",
      "name": "busca evento",
      "alwaysOutputData": true,
      "credentials": {
        "supabaseApi": {
          "id": "8ZVTQjP2XHFeNXtM",
          "name": "bma"
        }
      }
    },
    {
      "parameters": {
        "conditions": {
          "options": {
            "caseSensitive": true,
            "leftValue": "",
            "typeValidation": "strict",
            "version": 2
          },
          "conditions": [
            {
              "id": "a485b9dc-ec0b-4fad-ad5e-3c65fa500da1",
              "leftValue": "={{ $json.status }}",
              "rightValue": "approved",
              "operator": {
                "type": "string",
                "operation": "equals",
                "name": "filter.operator.equals"
              }
            }
          ],
          "combinator": "and"
        },
        "options": {}
      },
      "type": "n8n-nodes-base.if",
      "typeVersion": 2.2,
      "position": [
        -460,
        0
      ],
      "id": "db58b516-6f40-42ec-b648-a97390dedf00",
      "name": "aprovado"
    },
    {
      "parameters": {
        "conditions": {
          "options": {
            "caseSensitive": true,
            "leftValue": "",
            "typeValidation": "strict",
            "version": 2
          },
          "conditions": [
            {
              "id": "f760240a-5458-4573-ad3c-58c2d997b90a",
              "leftValue": "={{ $json }}",
              "rightValue": "",
              "operator": {
                "type": "object",
                "operation": "notEmpty",
                "singleValue": true
              }
            }
          ],
          "combinator": "and"
        },
        "options": {}
      },
      "type": "n8n-nodes-base.if",
      "typeVersion": 2.2,
      "position": [
        -220,
        -240
      ],
      "id": "a79464b5-eee8-461e-8e8f-2a4221e746d6",
      "name": "existe1"
    },
    {
      "parameters": {
        "mode": "combine",
        "combineBy": "combineByPosition",
        "options": {}
      },
      "type": "n8n-nodes-base.merge",
      "typeVersion": 3.1,
      "position": [
        100,
        -20
      ],
      "id": "ea138a8e-dcb3-4024-a804-741d9c8c32ba",
      "name": "Merge"
    },
    {
      "parameters": {
        "tableId": "eventos_guru",
        "fieldsUi": {
          "fieldValues": [
            {
              "fieldId": "id_contato",
              "fieldValue": "={{ $('Trata webhook').item.json.contact.id }}"
            },
            {
              "fieldId": "id_oferta",
              "fieldValue": "={{ $('Trata webhook').item.json.items[0].offer.id }}"
            }
          ]
        }
      },
      "type": "n8n-nodes-base.supabase",
      "typeVersion": 1,
      "position": [
        80,
        -220
      ],
      "id": "636d235d-d3db-40db-aa35-2a64fa7a9b53",
      "name": "add evento",
      "credentials": {
        "supabaseApi": {
          "id": "8ZVTQjP2XHFeNXtM",
          "name": "bma"
        }
      }
    },
    {
      "parameters": {
        "conditions": {
          "options": {
            "caseSensitive": true,
            "leftValue": "",
            "typeValidation": "strict",
            "version": 2
          },
          "conditions": [
            {
              "id": "cdd13823-73cd-4131-930b-63f44db6fc9c",
              "leftValue": "={{ $item(\"0\").$node[\"busca evento\"].json }}",
              "rightValue": "",
              "operator": {
                "type": "object",
                "operation": "empty",
                "singleValue": true
              }
            }
          ],
          "combinator": "and"
        },
        "options": {}
      },
      "type": "n8n-nodes-base.filter",
      "typeVersion": 2.2,
      "position": [
        560,
        -260
      ],
      "id": "86c56054-de47-4046-92f6-ed927128477d",
      "name": "novo1"
    }
  ],
  "pinData": {
    "Webhook": [
      {
        "json": {
          "headers": {
            "host": "webhook.josepbijari.com",
            "user-agent": "digitalmanager.guru (dev@digitalmanager.guru)",
            "content-length": "3987",
            "content-type": "application/json",
            "x-forwarded-for": "34.148.82.21",
            "x-forwarded-host": "webhook.josepbijari.com",
            "x-forwarded-port": "443",
            "x-forwarded-proto": "https",
            "x-forwarded-server": "869fd5766395",
            "x-real-ip": "34.148.82.21",
            "x-request-id": "9fdcd2ae-63f1-4f8d-9240-ebfe95c405a2",
            "accept-encoding": "gzip"
          },
          "params": {},
          "query": {},
          "body": {
            "affiliations": [],
            "api_token": "4MOQW1GNtH0Ok8F0XNVXJnRXiFt33bbFq4l3MLri",
            "checkout_url": "https://clkdmg.site/pay/9fd8a114-9f2c-4f4a-92ec-65b6b0776836",
            "contact": {
              "id": "9fdaefcd-2e90-42b4-85a0-53b0756c285b",
              "name": "Raysa Freitas",
              "company_name": "",
              "email": "raysa.bma@gmail.com",
              "doc": "12951995725",
              "phone_number": "21991526973",
              "phone_local_code": "55",
              "address": "Rua Tailândia",
              "address_number": "419",
              "address_comp": "Casa 1",
              "address_district": "Brás de Pina",
              "address_city": "Rio de Janeiro",
              "address_state": "RJ",
              "address_state_full_name": "RJ",
              "address_country": "BR",
              "address_zip_code": "21011350",
              "lead": []
            },
            "contracts": [],
            "dates": {
              "canceled_at": null,
              "confirmed_at": "2025-09-12T20:08:39Z",
              "created_at": "2025-09-12T20:07:56Z",
              "expires_at": "2025-09-13T03:00:00Z",
              "ordered_at": "2025-09-12T20:07:33Z",
              "unavailable_until": "2025-10-12T20:08:39Z",
              "updated_at": "2025-09-12T20:09:10Z",
              "warranty_until": "2025-10-12T20:08:39Z"
            },
            "ecommerces": [],
            "extras": {
              "accepted_terms_url": 0,
              "accepted_privacy_policy_url": 0
            },
            "id": "9fdcd208-7ffe-4621-a394-0ace4a03fb17",
            "infrastructure": {
              "ip": "187.67.200.69",
              "city": "rio de janeiro",
              "host": "clkdmg.site",
              "ga_id": "GA1.1.461835163.1722346833",
              "region": "rj",
              "country": "BR",
              "user_agent": "Mozilla/5.0 (Linux; Android 10; K) AppleWebKit/537.36 (KHTML, like Gecko) Chrome/140.0.0.0 Mobile Safari/537.36",
              "city_lat_long": "-22.906847,-43.172897",
              "facebook_browser_id": "fb.1.1757626480803.59795019686759271"
            },
            "invoice": [],
            "is_order_bump": 0,
            "is_reissue": 0,
            "items": [
              {
                "id": "1757446431",
                "image_url": "https://storage.googleapis.com/disk.clkdmg.site/clients/9ae96ffc-5ae6-4368-ad95-2a28f5b8a4e1/images/products/9fd89ed7-ecf2-4422-8287-2effdc216187.png",
                "internal_id": "9fd6bd06-f2aa-44ef-a15c-94c0fd020e4d",
                "marketplace_id": "1757446431",
                "marketplace_name": "pagarme2",
                "name": "IP EXPRESS - Setembro",
                "offer": {
                  "id": "9fd8a114-9f2c-4f4a-92ec-65b6b0776836",
                  "name": "teste"
                },
                "producer": {
                  "contact_email": null,
                  "marketplace_id": "1703273968",
                  "name": "Incorporacao Na Pratica"
                },
                "qty": 1,
                "total_value": 1,
                "type": "product",
                "unit_value": 1
              }
            ],
            "last_transaction": [],
            "payment": {
              "affiliate_value": 0,
              "acquirer": {
                "code": "0",
                "message": "",
                "name": "none",
                "nsu": "4096880616",
                "tid": "4096880616"
              },
              "can_try_again": 1,
              "coupon": null,
              "currency": "BRL",
              "discount_value": 0,
              "gross": 1,
              "installments": {
                "value": 1,
                "qty": 1,
                "interest": 0
              },
              "marketplace_id": "ch_nz2bVW4hPlFKxNed",
              "marketplace_name": "pagarme2",
              "marketplace_value": 0.01,
              "method": "pix",
              "net": 0.99,
              "processing_times": {
                "started_at": "2025-09-12T20:08:12.287Z",
                "finished_at": "2025-09-12T20:08:13.652Z",
                "delay_in_seconds": 1
              },
              "refund_reason": "",
              "refuse_reason": " (0)",
              "tax": {
                "value": 0,
                "rate": 0
              },
              "total": 1,
              "pix": {
                "qrcode": {
                  "signature": "00020101021226820014br.gov.bcb.pix2560pix.stone.com.br/pix/v2/fdd4c821-1893-4332-a415-bb510904e0f752040000530398654041.005802BR5925Carolina Caribe Negocios 6014RIO DE JANEIRO622905250bdf62853fd18bce2c35d5e656304C24C",
                  "url": "https://clkdmg.site/api/checkout/invoices/9fdcd208-7ffe-4621-a394-0ace4a03fb17/qrcodes/pix"
                },
                "expiration_date": "2025-09-13"
              }
            },
            "product": {
              "id": "1757446431",
              "image_url": "https://storage.googleapis.com/disk.clkdmg.site/clients/9ae96ffc-5ae6-4368-ad95-2a28f5b8a4e1/images/products/9fd89ed7-ecf2-4422-8287-2effdc216187.png",
              "internal_id": "9fd6bd06-f2aa-44ef-a15c-94c0fd020e4d",
              "marketplace_id": "1757446431",
              "marketplace_name": "pagarme2",
              "name": "IP EXPRESS - Setembro",
              "offer": {
                "id": "9fd8a114-9f2c-4f4a-92ec-65b6b0776836",
                "name": "teste"
              },
              "producer": {
                "marketplace_id": "1703273968",
                "name": "Incorporacao Na Pratica",
                "contact_email": ""
              },
              "qty": 1,
              "total_value": 1,
              "type": "product",
              "unit_value": 1
            },
            "self_attribution": null,
            "shipment": {
              "carrier": "",
              "service": "",
              "tracking": "",
              "value": 0,
              "status": "",
              "delivery_time": ""
            },
            "shipping": {
              "name": " - ",
              "value": 0
            },
            "source": {
              "source": null,
              "checkout_source": null,
              "utm_source": null,
              "utm_campaign": null,
              "utm_medium": null,
              "utm_content": null,
              "utm_term": null,
              "pptc": []
            },
            "status": "approved",
            "subscription": [],
            "type": "producer",
            "webhook_type": "transaction"
          },
          "webhookUrl": "https://webhook.josepbijari.com/webhook/compradores-ip-express",
          "executionMode": "production"
        }
      }
    ]
  },
  "settings": {
    "executionOrder": "v1"
  },
  "shared": [
    {
      "updatedAt": "2025-09-10T18:03:23.683Z",
      "createdAt": "2025-09-10T18:03:23.683Z",
      "role": "workflow:owner",
      "workflowId": "IWuNDg2leQAk25ev",
      "projectId": "AxNpta0sA2v4gJ2a"
    }
  ],
  "staticData": null,
  "tags": [],
  "triggerCount": 1,
  "updatedAt": "2025-09-12T20:15:53.954Z",
  "versionId": "30df5986-3284-41e3-b045-52f16f7af6ba"
}